bpca/__init__.py
bpca/_bpca.py
bpca/_core.py
bpca/_utils.py
bpca-0.0.3.dist-info/METADATA
bpca-0.0.3.dist-info/WHEEL
bpca-0.0.3.dist-info/licenses/LICENSE
bpca-0.0.3.dist-info/RECORD
