Metadata-Version: 2.4
Name: bpca
Version: 0.0.3
Summary: Bayesian Principal Component Analysis
Project-URL: Documentation, https://bpca.readthedocs.io/
Project-URL: Homepage, https://github.com/lucas-diedrich/bpca
Project-URL: Source, https://github.com/lucas-diedrich/bpca
Author: lucas-diedrich
Maintainer-email: lucas-diedrich <diedrich@biochem.mpg.de>
License:             GNU GENERAL PUBLIC LICENSE
License-File: LICENSE
Classifier: Programming Language :: Python :: 3 :: Only
Classifier: Programming Language :: Python :: 3.10
Classifier: Programming Language :: Python :: 3.11
Classifier: Programming Language :: Python :: 3.12
Classifier: Programming Language :: Python :: 3.13
Classifier: Programming Language :: Python :: 3.14
Requires-Python: >=3.10
Requires-Dist: numpy
Requires-Dist: session-info2
